devtools_list_to_json/__init__.py
devtools_list_to_json-1.0.1.dist-info/METADATA
devtools_list_to_json-1.0.1.dist-info/WHEEL
devtools_list_to_json-1.0.1.dist-info/top_level.txt
devtools_list_to_json-1.0.1.dist-info/RECORD
