Metadata-Version: 2.1
Name: devtools_list_to_json
Version: 1.0.1
Summary: List to JSON array converter
Home-page: https://devtools.at/tools/list-to-json
Author: DevTools.at
Author-email: hello@devtools.at
Project-URL: Homepage, https://devtools.at/tools/list-to-json
Project-URL: Repository, https://github.com/devtools-at/list-to-json
Classifier: Development Status :: 4 - Beta
Classifier: Intended Audience :: Developers
Classifier: License :: OSI Approved :: MIT License
Classifier: Programming Language :: Python :: 3
Requires-Python: >=3.8
